data_job_crawler/__init__.py
data_job_crawler/config/__init__.py
data_job_crawler/config/definitions.py
data_job_crawler/crawler/__init__.py
data_job_crawler/crawler/items.py
data_job_crawler/crawler/middlewares.py
data_job_crawler/crawler/pipelines.py
data_job_crawler/crawler/settings.py
data_job_crawler/crawler/spiders/MAD.py
data_job_crawler/crawler/spiders/__init__.py
data_job_crawler/crawler/spiders/oldwttj.py
data_job_crawler/crawler/spiders/spotify.py
data_job_crawler/crawler/spiders/spotify_links.py
data_job_crawler/crawler/spiders/wttj.py
data_job_crawler/crawler/spiders/wttj_links.py
data_job_crawler/file.log
data_job_crawler/helpers/extract_links.py
data_job_crawler/helpers/upload_to_s3.py
data_job_crawler/scrapy.cfg
data_job_crawler-1.1.0.dist-info/METADATA
data_job_crawler-1.1.0.dist-info/WHEEL
data_job_crawler-1.1.0.dist-info/RECORD
