Metadata-Version: 2.1
Name: data-job-crawler
Version: 1.1.0
Summary: 
Author: Donor
Author-email: donorfelita@msn.com
Requires-Python: >=3.9,<4.0
Classifier: Programming Language :: Python :: 3
Classifier: Programming Language :: Python :: 3.9
Classifier: Programming Language :: Python :: 3.10
Classifier: Programming Language :: Python :: 3.11
Requires-Dist: playwright (>=1.24.1,<2.0.0)
Requires-Dist: psycopg2-binary (>=2.9.5,<3.0.0)
Requires-Dist: scrapy (>=2.6.2,<3.0.0)
Requires-Dist: scrapy-playwright
